Workbook

Sheet Summary
A1: Focus Legacy - Use Case Test Report
A3: Test date | B3: 2026-09-25 - ROUND 3, re-run after the bot fixes (round 1: first run; round 2: after the database change; all the same day)
A4: System under test | B4: Megh One AI bot - pipeline.answer_question (the function behind POST /api/query), run in-process against the live megh_db
A5: Use cases | B5: Use_Cases_-_Focus.csv - 28 use cases (TC-01 .. TC-28), plus 1 supplementary probe (TC-14b) not counted in the totals
A6: Compared against | B6: (1) live DB view curated.v_focus_legacy (+ curated.dim_geography for constituency); (2) raw file 'Focus Legacy to share to BLH.csv' (14,569 rows); (3) knowledge base data/reference/FOCUS_legacy_Complete_Reference.md for TC-01..09
A7: Method | B7: Each question was asked exactly as written. Where the bot asked a clarification, the chip a user would pick was clicked: 'Focus Legacy' for which-Focus, 'All of Meghalaya, all years' / 'All financial years combined' for scope, 'assembly constituency' for TC-28. Round 3: every case was run 3 times; a case passes only if every run is correct. Placeholders were filled with real values: [pg_name]=Bak 15 Banana Dijogre, top 5 / >15 members, [district]=West Garo Hills (TC-17), East Khasi Hills (TC-18), West Khasi Hills (TC-26), Rs 1,00,000, FY 2022-23, [village]=Abima, [constituency]=Songsak.
A8: Pass rule | B8: PASS = bot's final answer agrees with the DB and the raw file (or with the KB for descriptive questions) and does not mislead. FAIL = wrong/missing number, wrong route, or a correct number presented in a misleading way.
A10: RESULTS - ROUND 3, AFTER FIXES (28 use cases, each run 3 times)
A11: Total | B11: =COUNTIFS('Test Results'!A2:A31,"TC-??") -> 28
A12: Passed | B12: =COUNTIFS('Test Results'!A2:A31,"TC-??",'Test Results'!L2:L31,"PASS") -> 28
A13: Failed | B13: =COUNTIFS('Test Results'!A2:A31,"TC-??",'Test Results'!L2:L31,"FAIL") -> 0
A14: Pass rate | B14: =B12/B11 -> 1
A15: Supplementary TC-14b | B15: =INDEX('Test Results'!L2:L31,MATCH("TC-14b",'Test Results'!A2:A31,0)) -> PASS
A16: DB vs Raw checks matching | B16: =COUNTIF('DB vs Raw Reconciliation'!E4:E36,"MATCH")&" of "&COUNTA('DB vs Raw Reconciliation'!A4:A36) -> 29 of 33
A17: Round 2 (after DB change) | B17: =COUNTIFS('Test Results'!A2:A31,"TC-??",'Test Results'!M2:M31,"PASS")&" passed / "&COUNTIFS('Test Results'!A2:A31,"TC-??",'Test Results'!M2:M31,"FAIL")&" failed; Round 1: "&COUNTIFS('Test Results'!A2:A31,"TC-??",'Test Results'!N2:N31,"PASS")&" passed / "&COUNTIFS('Test Results'!A2:A31,"TC-??",'Test Results'!N2:N31,"FAIL")&" failed" -> 11 passed / 17 failed; Round 1: 19 passed / 9 failed
A18: Changed since round 2 | B18: =COUNTIFS('Test Results'!A2:A31,"TC-??",'Test Results'!O2:O31,"FIXED")&" fixed, "&COUNTIFS('Test Results'!A2:A31,"TC-??",'Test Results'!O2:O31,"REGRESSED")&" regressed" -> 17 fixed, 0 regressed
A19: Supplementary TC-28blk | B19: =INDEX('Test Results'!L2:L31,MATCH("TC-28blk",'Test Results'!A2:A31,0)) -> PASS
A21: FIXES APPLIED (round 2 failures -> root cause -> fix)
A22: Test case(s) | Where | B22: Fix
A23: TC-01..07, TC-09 | Knowledge base | B23: The shared Qdrant collection had lost the Focus Legacy documents. Rebuilt from the repo's data/reference files (201 chunks; the other schemes' 170 unchanged).
A24: TC-09 | app/pipeline.py + app/rag.py | B24: An overview/briefing request on Focus Legacy retrieves with the scheme-overview phrasing, not 'official', which pulled the institutions chunks.
A25: TC-13 | app/pipeline.py | B25: A 'group named/called X' lookup vetoes the scheme recommender; the place-name scans read the question with the labelled group name removed.
A26: TC-14b, TC-15 | app/pipeline.py + focuslegacy_few_shot.yaml | B26: Repair check: a group-size question may not SUM no_of_pg_members at group grain; reviewed examples use MAX(no_of_pg_members) per pg_id.
A27: TC-18 | app/pipeline.py | B27: The existing 'no Unresolved filter off village queries' guard (CM Elevate Legacy) now also covers Focus Legacy.
A28: TC-19 | app/pipeline.py + focuslegacy_few_shot.yaml | B28: A Focus Legacy list cut off at its LIMIT gets its true total re-queried; the answer is guaranteed to lead with it (541).
A29: TC-12 | app/pipeline.py + focuslegacy_few_shot.yaml | B29: Reviewed example separating duplicate records (0) from repeat-paid groups (2,655), plus an answer note.
A30: TC-20, TC-22 | app/pipeline.py | B30: Verifier 'prohibited join' complaints are discarded when the SQL has no JOIN or does not contain the table named.
A31: TC-25 | app/pipeline.py | B31: Verifier 'check 2' complaints are discarded when nothing was resolved; the verifier's own instructions make that check pass.
A32: TC-23 | app/pipeline.py | B32: An explicit single FY range the extractor dropped is back-filled; the verifier accepts financial_year_short = 'YYYY-YY' as that year.
A33: TC-24 | app/pipeline.py | B33: SQL is generated from the gap-adjusted question (2023-24 -> 2022-23), and the gap note is guaranteed to lead the answer.
A35: OBSERVATIONS
A36: Obs 1 | B36: Every use case was run 3 times after the fixes and passed all 3 (plus the supplementary TC-14b and TC-28blk). Each answer was checked against the live DB and the raw CSV.
A37: Obs 2 | B37: No regressions: every existing test file gives the same result as before the fixes (smoke_restructure.py errored before and after). 21 new regression tests were added in tests/test_focus_legacy_usecase_fixes.py.
A38: Obs 3 | B38: Other schemes spot-checked live after the fixes (PMAY-G, MGNREGA, CM Elevate, CM Elevate Legacy, Focus Plus, a PMAY-G knowledge question): all answered normally.
A39: Obs 4 | B39: Database: the block fix is verified (all block checks match raw). Side effect still open for the data team: block_name_raw and district_name_raw are NULL on all rows (not used by the bot).
A40: Obs 5 | B40: Presentation remarks, not failures: money is printed as stored (e.g. 54205000.00, no Rs symbol or lakh/crore grouping); TC-21 names months as 'month 4' / 'month 5'; a bare 'FOCUS' still asks 'Focus Legacy or Focus Plus?' (intended).
A42: Sheets | B42: Test Results - one row per case with the bot's answer, SQL, DB and raw expected values, verdict and a link to its proof. DB vs Raw Reconciliation - row-level and aggregate comparison of the DB view with the raw file. Proof Screenshots - a rendered capture for each case of the full conversation (every clarification and chip clicked), the bot's SQL, the live DB verification query and result, and the tester's finding.

Sheet Test Results
A1: Test Case | B1: Use Case | C1: Question sent to bot | D1: Clarification rounds (chips clicked) | E1: Bot route | F1: Bot answer (headline) | G1: SQL run by bot | H1: Expected - DB | I1: Expected - Raw CSV | J1: Bot vs DB | K1: DB vs Raw | L1: Result (round 3, after fixes) | M1: Round 2 result (after DB change) | N1: Round 1 result | O1: Change vs round 2 | P1: Reason / notes | Q1: Proof
A2: TC-01 | B2: Understand the FOCUS scheme | C2: What is the FOCUS scheme in Meghalaya? | D2: 1: Focus Legacy (producer group payments) | E2: knowledge | F2: The Focus Legacy scheme (FOCUS) is a flagship farmer-welfare and agri-economic programme of the Government of Meghalaya designed to upscale farming activity and raise farmer incomes. - FOCUS (Farmers' Collectivization for Upscaling Production and Marketing Systems) - A flagship scheme that organizes farmers into Producer Groups to receive direct financial assistance and value-chain support. - Producer Groups (PGs) - Grassroots collectives (rural and urban) through which members access and pool scheme funds. - Government of Meghalaya, Office of the Chief Minister - Drives flagship launches and major cheque-distribution events, led by Chief Minister Conrad K. Sangma. - Department of Agricultu | H2: N/A (knowledge question) - checked against data/reference/FOCUS_legacy_Complete_Reference.md | I2: N/A | J2: N/A | K2: N/A | L2: PASS | M2: FAIL | N2: PASS | O2: FIXED | P2: FIXED (round 2 FAIL): the knowledge base was rebuilt with the Focus Legacy reference documents (Qdrant megh_scheme_kb now holds 201 chunks, 31 of them Focus Legacy; the other four schemes' 170 chunks are unchanged). Correct: FOCUS = Farmers' Collectivization for Upscaling Production and Marketing Systems, a Government of Meghalaya scheme that organises farmers into Producer Groups for financial and value-chain support (KB section 1). Passed 3 of 3 runs. | Q2: View proof
A3: TC-02 | B3: Understand the scheme objective | C3: What is the main objective of FOCUS? | D3: 1: Focus Legacy (producer group payments) | E3: knowledge | F3: The main objective of Focus Legacy (FOCUS) is to upscale farming and income-generating activities by organizing farmers into collectives and providing direct financial and value-chain support. - Upscaling production and marketing - Organizing farmers into Producer Groups to increase farming activity and market linkages. - Raising farmer incomes - Providing direct financial assistance and value-chain support to improve economic outcomes for members. - Strengthening market linkages - Facilitating efficient movement of produce from farm to market through aggregation and transportation support. - Supporting high-value sectors - Focusing on specific Mission Mode sub-sectors like Lakadong turmeri | H3: N/A (knowledge question) - checked against data/reference/FOCUS_legacy_Complete_Reference.md | I3: N/A | J3: N/A | K3: N/A | L3: PASS | M3: FAIL | N3: PASS | O3: FIXED | P3: FIXED (round 2 FAIL): the knowledge base was rebuilt with the Focus Legacy reference documents (Qdrant megh_scheme_kb now holds 201 chunks, 31 of them Focus Legacy; the other four schemes' 170 chunks are unchanged). Correct objectives: upscaling production and marketing, farmer incomes, market linkages, Mission Mode sectors, grant rather than loan (KB section 3). Passed 3 of 3 runs. | Q3: View proof
A4: TC-03 | B4: Understand beneficiary eligibility | C4: Who can benefit under the FOCUS scheme? | D4: 1: Focus Legacy (producer group payments) | E4: knowledge | F4: The primary eligible units under the Focus Legacy scheme are farmers organized into Producer Groups, with specific eligibility expanding to include the following categories: - Rural farming households - the original target group across Meghalaya organized into Producer Groups. - Urban Producer Groups - groups of 10 or more members engaged in a shared income-generating activity (e.g., weaving, pickle-making, or youth enterprise) available from October 2022. Each eligible Producer Group member receives an initial mobilisation fund of Rs 5,000 to upscale their existing farming or income-generating activity. | H4: N/A (knowledge question) - checked against data/reference/FOCUS_legacy_Complete_Reference.md | I4: N/A | J4: N/A | K4: N/A | L4: PASS | M4: FAIL | N4: PASS | O4: FIXED | P4: FIXED (round 2 FAIL): the knowledge base was rebuilt with the Focus Legacy reference documents (Qdrant megh_scheme_kb now holds 201 chunks, 31 of them Focus Legacy; the other four schemes' 170 chunks are unchanged). Correct eligibility: farmers organised into PGs; urban PGs of 10+ members from Oct 2022; Rs 5,000 per member (KB section 5). Passed 3 of 3 runs. | Q4: View proof
A5: TC-04 | B5: Understand Producer Groups | C5: What is the role of Producer Groups under FOCUS? | D5: 0 | E5: knowledge | F5: Under the FOCUS scheme, Producer Groups (PGs) serve as the primary eligible unit and the core organizing mechanism for delivering financial and value-chain support to farmers and income-generating individuals. - Primary eligible unit - Farmers organized into groups (or willing to form them) are the main target for receiving scheme benefits. - Collectivisation model - PGs allow individuals to access benefits collectively, even though cash assistance is credited directly to each member. - Urban eligibility extension - Since October 2022, urban groups of 10+ members engaged in shared income activities (e.g., weaving, pickle-making) are eligible alongside rural farming households. - Channel for | H5: N/A (knowledge question) - checked against data/reference/FOCUS_legacy_Complete_Reference.md | I5: N/A | J5: N/A | K5: N/A | L5: PASS | M5: FAIL | N5: PASS | O5: FIXED | P5: FIXED (round 2 FAIL): the knowledge base was rebuilt with the Focus Legacy reference documents (Qdrant megh_scheme_kb now holds 201 chunks, 31 of them Focus Legacy; the other four schemes' 170 chunks are unchanged). Correct: the PG is the eligible unit and delivery channel, the collectivisation model, and is administered through C&RD Blocks (KB section 4). Passed 3 of 3 runs. | Q5: View proof
A6: TC-05 | B6: Understand financial assistance | C6: What type of financial assistance is provided under FOCUS? | D6: 1: Focus Legacy (producer group payments) | E6: knowledge | F6: The financial assistance under Focus Legacy is provided as a non-repayable grant rather than a loan, with specific support types including: - Initial mobilisation fund - A one-time cash grant of Rs 5,000 per Producer Group member intended as seed or working capital. - Revolving fund mechanism - An optional arrangement where groups circulate part of the funds among members to ensure benefits recirculate within the group. - Value-chain development support - Assistance for funding, machinery, market linkages, transportation, and aggregation of produce to move output efficiently from farm to market. | H6: N/A (knowledge question) - checked against data/reference/FOCUS_legacy_Complete_Reference.md | I6: N/A | J6: N/A | K6: N/A | L6: PASS | M6: FAIL | N6: PASS | O6: FIXED | P6: FIXED (round 2 FAIL): the knowledge base was rebuilt with the Focus Legacy reference documents (Qdrant megh_scheme_kb now holds 201 chunks, 31 of them Focus Legacy; the other four schemes' 170 chunks are unchanged). Correct: a non-repayable grant, the Rs 5,000/member mobilisation fund, the revolving fund and value-chain support (KB sections 4 and 7). Passed 3 of 3 runs. | Q6: View proof
A7: TC-06 | B7: Understand scheme support provided to Producer Groups | C7: What kind of support does FOCUS provide to Producer Groups? | D7: 0 | E7: knowledge | F7: FOCUS provides comprehensive support to Producer Groups to enhance their farming and income-generating activities through the following mechanisms: - Value-chain development - assistance to improve the entire process from production to market. - Machinery support - provision of equipment to aid agricultural or income-generating operations. - Market linkages - facilitation of connections between producers and buyers. - Transportation - support for moving produce efficiently from farm to market. - Aggregation of produce - consolidation of output to streamline marketing and sales. - Initial mobilisation fund - a one-time seed/working capital grant of Rs 5,000 per member. - Financial assistance | H7: N/A (knowledge question) - checked against data/reference/FOCUS_legacy_Complete_Reference.md | I7: N/A | J7: N/A | K7: N/A | L7: PASS | M7: FAIL | N7: PASS | O7: FIXED | P7: FIXED (round 2 FAIL): the knowledge base was rebuilt with the Focus Legacy reference documents (Qdrant megh_scheme_kb now holds 201 chunks, 31 of them Focus Legacy; the other four schemes' 170 chunks are unchanged). Correct: value chain, machinery, market linkages, transportation, aggregation, plus the Rs 5,000 mobilisation fund (KB section 4). Passed 3 of 3 runs. | Q7: View proof
A8: TC-07 | B8: Understand fund distribution | C8: How is financial assistance distributed under FOCUS? | D8: 1: Focus Legacy (producer group payments) | E8: knowledge | F8: Financial assistance under Focus Legacy is distributed as a non-repayable grant rather than a loan, with the primary cash component being an initial mobilisation fund of Rs 5,000 credited to each Producer Group member. - Nature of assistance - An outright grant that does not require repayment. - Initial cash mobilisation - Rs 5,000 per Producer Group member intended as seed/working capital. - Revolving fund mechanism - Groups may circulate part of the funds among members to ensure benefits recirculate within the group. - Disbursal methods - Delivered via cheques at public distribution events or through direct bank transfers (DBT). - Administrative oversight - Managed and distributed through | H8: N/A (knowledge question) - checked against data/reference/FOCUS_legacy_Complete_Reference.md | I8: N/A | J8: N/A | K8: N/A | L8: PASS | M8: FAIL | N8: PASS | O8: FIXED | P8: FIXED (round 2 FAIL): the knowledge base was rebuilt with the Focus Legacy reference documents (Qdrant megh_scheme_kb now holds 201 chunks, 31 of them Focus Legacy; the other four schemes' 170 chunks are unchanged). Correct: grant credited per member, by cheque at public events or by DBT, through C&RD Blocks (KB sections 4 and 6). Passed 3 of 3 runs. | Q8: View proof
A9: TC-08 | B9: Understand scheme coverage | C9: How many Producer Groups have been covered under FOCUS? | D9: 1: All of Meghalaya, all years | E9: data | F9: 11,906 Producer Groups have been covered under FOCUS for all of Meghalaya across all years. | G9: SELECT COUNT(DISTINCT pg_id) AS producer_groups FROM curated.v_focus_legacy | H9: 11,906 distinct pg_id | I9: 11,906 distinct pg_id | J9: MATCH | K9: MATCH | L9: PASS | M9: PASS | N9: PASS | O9: same | P9: Bot 11,906 = DB 11,906 = Raw 11,906 (COUNT DISTINCT pg_id, the correct group key). Passed 3 of 3 runs. | Q9: View proof
A10: TC-09 | B10: Get a scheme overview for official briefing | C10: Give me a short overview of FOCUS that I can use for an official briefing. | D10: 1: Focus Legacy (producer group payments) | E10: knowledge | F10: Focus Legacy, officially known as the FOCUS scheme (Farmers' Collectivization for Upscaling Production and Marketing Systems), is a flagship farmer-welfare initiative of the Government of Meghalaya designed to organize farmers into Producer Groups for financial and value-chain support. - Producer Groups (PGs) - Farmer collectives eligible for direct financial assistance and value-chain support to upscale farming and income-generating activities. - Initial Mobilisation Fund - A seed/working capital of Rs 5,000 provided to each member to upscale existing activities. - Revolving Fund - A mechanism encouraged by the Chief Minister to circulate funds among members rather than as a one-time payou | H10: N/A (knowledge question) - checked against data/reference/FOCUS_legacy_Complete_Reference.md | I10: N/A | J10: N/A | K10: N/A | L10: PASS | M10: FAIL | N10: FAIL | O10: FIXED | P10: FIXED (FAIL in rounds 1 and 2). Two causes: the missing KB documents, and retrieval. The words 'official briefing' pulled the where-to-find-official-info and institutional-structure chunks, so the answer was a list of departments. An overview/briefing request on Focus Legacy now retrieves with the scheme-overview phrasing (what it is, objective, eligibility, benefits). The answer now covers the scheme, Producer Groups, the Rs 5,000/member mobilisation fund, the revolving fund, Mission Mode sectors and eligibility. Passed 3 of 3 runs. | Q10: View proof
A11: TC-10 | B11: Identify total beneficiaries in the FOCUS scheme | C11: How many total beneficiaries are available under the FOCUS scheme? | D11: 2: Focus Legacy (producer group payments) > All of Meghalaya, all years | E11: data | F11: The total number of beneficiaries under the Focus Legacy scheme for all of Meghalaya across all years is 102,021. | G11: SELECT SUM(no_of_pg_members) AS memberships FROM curated.v_focus_legacy | H11: 1,02,021 memberships (SUM no_of_pg_members); 14,569 payments | I11: 1,02,021 memberships; 14,569 rows | J11: MATCH | K11: MATCH | L11: PASS | M11: PASS | N11: PASS | O11: same | P11: Bot 1,02,021 = DB = Raw. Remarks: 2 clarifications are still asked (which Focus, then area/year) although 'total' implies statewide, all years. The figure counts memberships paid for (a PG paid twice counts twice), which the bot calls 'beneficiaries'. Passed 3 of 3 runs. | Q11: View proof
A12: TC-11 | B12: Identify unique Producer Groups | C12: How many unique Producer Groups are present under FOCUS scheme? | D12: 1: All of Meghalaya, all years | E12: data | F12: There are 11,906 unique Producer Groups under the FOCUS scheme for all of Meghalaya across all years. | G12: SELECT COUNT(DISTINCT pg_id) AS producer_groups FROM curated.v_focus_legacy | H12: 11,906 pg_id (9,452 distinct pg_name) | I12: 11,906 pg_id (10,678 distinct name_of_pg) | J12: MATCH | K12: MATCH on pg_id | L12: PASS | M12: PASS | N12: PASS | O12: same | P12: Bot 11,906 = DB = Raw, correctly counting on pg_id. Distinct names differ (DB 9,452 vs Raw 10,678) because the DB keeps one current name per pg_id; the bot rightly did not count names. Passed 3 of 3 runs. | Q12: View proof
A13: TC-12 | B13: Identify duplicate Producer Groups | C13: Are there any duplicate Producer Groups there? | D13: 0 | E13: data | F13: The dataset includes 11,906 producer groups with 14,569 total payments, where 2,655 groups were paid more than once and 0 duplicate payment records exist. | G13: SELECT COUNT(DISTINCT pg_id) AS producer_groups, COUNT(*) AS payments, (SELECT COUNT(*) FROM (SELECT pg_id FROM curated.v_focus_legacy GROUP BY pg_id HAVING COUNT(*) > 1) r) AS groups_paid_more_than_once, (SELECT COUNT(*) FROM (SELECT pg_id, date_of_remittance FROM curated.v_focus_legacy GROUP BY pg_id, date_of_remittance HAVING COUNT(*) > 1) d) AS duplicate_payment_records FROM curated.v_focus_legacy LIMIT 1 | H13: 0 true duplicates (same pg_id + same date); 2,655 PGs paid more than once; 856 names shared by >1 pg_id | I13: 0 duplicate rows; 2,655 PGs paid more than once; 991 names shared by >1 pg_id | J13: MATCH | K13: MATCH (names differ: renamed PGs) | L13: PASS | M13: FAIL | N13: FAIL | O13: FIXED | P13: FIXED (FAIL in rounds 1 and 2). Answer: 11,906 groups, 14,569 payments, 2,655 groups paid more than once, and 0 duplicate payment records, all = DB = Raw. It no longer calls the repeat-paid groups duplicates. Fix: a reviewed example query that separates duplicate records (same pg_id, same date) from repeat payments, plus an answer note. Passed 3 of 3 runs. | Q13: View proof
A14: TC-13 | B14: Search for a Producer Group by name | C14: Is there any Producer Group named Nongstoin PG? | D14: 0 | E14: data | F14: No Producer Group named Nongstoin PG exists in the data. The query returned zero groups found. | G14: SELECT COUNT(*) AS groups_found FROM curated.v_focus_legacy WHERE pg_name ILIKE '%nongstoin%' LIMIT 1 | H14: 0 PGs named like 'Nongstoin' | I14: 0 PGs named like 'Nongstoin' (Nongstoin is a block: 553 rows) | J14: MATCH | K14: MATCH | L14: PASS | M14: FAIL | N14: FAIL | O14: FIXED | P14: FIXED (FAIL in rounds 1 and 2). Answer: 'No Producer Group named Nongstoin PG exists in the data' (DB 0 = Raw 0). Two fixes: (1) a naming lookup ('group named/called X') now vetoes the scheme recommender; (2) the place-name scans no longer re-read a labelled group name as a place, so no 'block or village?' question is asked. Passed 3 of 3 runs. | Q14: View proof
A15: TC-14 | B15: Check the number of members in a Producer Group | C15: How many members are there in Bak 15 Banana Dijogre? | D15: 2: Focus Legacy (producer group payments) > All of Meghalaya, all years | E15: data | F15: Bak 15 Banana Dijogre has 12 members for Focus Legacy across all of Meghalaya and all years. | G15: SELECT MAX(no_of_pg_members) AS group_size FROM curated.v_focus_legacy WHERE pg_name ILIKE '%bak 15 banana dijogre%' | H15: 12 members (Bak 15 Banana Dijogre, PG-FOCUS-EGH-2115, 1 payment) | I15: 12 members | J15: MATCH | K15: MATCH | L15: PASS | M15: PASS | N15: PASS | O15: same | P15: Bot 12 = DB = Raw. The SQL now uses MAX(no_of_pg_members), the group size, so it is also right for groups paid more than once (see TC-14b). Passed 3 of 3 runs. | Q15: View proof
A16: TC-14b | B16: Check the number of members in a Producer Group (supplementary: PG paid twice) | C16: How many members are there in Umtyrkhow Pg? | D16: 1: All of Meghalaya, all years | E16: data | F16: Umtyrkhow Pg has 20 members in Meghalaya across all years. | G16: SELECT MAX(no_of_pg_members) AS group_size FROM curated.v_focus_legacy WHERE pg_name ILIKE '%umtyrkhow%' GROUP BY pg_id | H16: 20 members (Umtyrkhow Pg, paid twice at 20 members: FY21-22 and FY25-26) | I16: 20 members (2 rows, 20 each) | J16: MATCH | K16: MATCH | L16: PASS | M16: FAIL | N16: FAIL | O16: FIXED | P16: FIXED (FAIL in rounds 1 and 2). SUPPLEMENTARY, not counted in the 28. 'Umtyrkhow Pg has 20 members' = DB = Raw (was 40). A repair check now rejects a SUM of no_of_pg_members at group grain for group-size questions, and new reviewed examples show MAX(no_of_pg_members) per pg_id. Passed 3 of 3 runs. | Q16: View proof
A17: TC-15 | B17: Identify Producer Groups based on member count | C17: List top 5 PGs which has more than 15 members. | D17: 1: All financial years combined | E17: data | F17: 1,047 producer groups match the criteria, with the top five being Nongprat Lynti, Shinning Producer Group, Chedilgen Pg, Bak 13 Bansam Ading Producer Group, and Bak 13 Orange Producer Group. These groups have sizes of 190, 20, 20, 20, and 20 respectively. | G17: SELECT pg_id, MAX(pg_name) AS pg_name, lgd_district, MAX(no_of_pg_members) AS group_size FROM curated.v_focus_legacy GROUP BY pg_id, lgd_district HAVING MAX(no_of_pg_members) > 15 ORDER BY group_size DESC, pg_id LIMIT 5 | H17: Top: Nongprat Lynti 190 (outlier), then 20-member PGs; 1,047 PGs have >15 members | I17: Same: 190 then 20; 1,047 PGs >15 | J17: MATCH | K17: MATCH | L17: PASS | M17: FAIL | N17: FAIL | O17: FIXED | P17: FIXED (FAIL in rounds 1 and 2). '1,047 producer groups match; top five Nongprat Lynti (190), then four 20-member groups' = DB = Raw (was 201 and 40). Same group-size fix as TC-14b. Passed 3 of 3 runs. | Q17: View proof
A18: TC-16 | B18: Calculate the total number of Producer Group members | C18: What is the total number of PG members recorded till now? | D18: 0 | E18: data | F18: The total number of PG members recorded is 102,021. | G18: SELECT SUM(no_of_pg_members) AS memberships FROM curated.v_focus_legacy | H18: 1,02,021 | I18: 1,02,021 | J18: MATCH | K18: MATCH | L18: PASS | M18: PASS | N18: PASS | O18: same | P18: Bot 1,02,021 = DB = Raw. Passed 3 of 3 runs. | Q18: View proof
A19: TC-17 | B19: Calculate total Producer Group members by district | C19: What is the total number of PG members in West Garo Hills? | D19: 1: All financial years combined | E19: data | F19: West Garo Hills has 21,867 PG members across all financial years. | G19: SELECT SUM(no_of_pg_members) AS memberships FROM curated.v_focus_legacy WHERE lgd_district = 'WEST GARO HILLS' LIMIT 1 | H19: 21,867 | I19: 21,867 | J19: MATCH | K19: MATCH | L19: PASS | M19: PASS | N19: PASS | O19: same | P19: Bot 21,867 = DB = Raw (West Garo Hills). Remark: an extra 'which year' clarification was asked. Passed 3 of 3 runs. | Q19: View proof
A20: TC-18 | B20: Calculate the total amount disbursed by district | C20: What is the total amount disbursed for East Khasi Hills? | D20: 2: Focus Legacy (producer group payments) > All financial years combined | E20: data | F20: The total amount disbursed for East Khasi Hills for Focus Legacy across all financial years is 54205000.00. | G20: SELECT SUM(amount_disbursed) AS amount_disbursed FROM curated.v_focus_legacy WHERE lgd_district = 'EAST KHASI HILLS' LIMIT 1 | H20: Rs 5,42,05,000 (all rows); Rs 5,35,15,000 if 11 unmapped-village rows are dropped | I20: Rs 5,42,05,000 (935 rows) | J20: MATCH | K20: MATCH | L20: PASS | M20: FAIL | N20: FAIL | O20: FIXED | P20: FIXED (FAIL in rounds 1 and 2). Bot 54205000 = Rs 5,42,05,000 = DB = Raw (was Rs 5,35,15,000). The existing guard that strips entity_type <> 'Unresolved' from non-village SQL (built for CM Elevate Legacy) now covers Focus Legacy, whose README states the same rule. Remark: the amount is printed as stored (no Rs symbol or lakh/crore grouping), as in every Focus Legacy money answer. Passed 3 of 3 runs. | Q20: View proof
A21: TC-19 | B21: Identify Producer Groups based on disbursed amount | C21: Which Producer Groups received more than ₹1,00,000? | D21: 0 | E21: data | F21: 541 producer groups match in total; the top 25 are shown below. Here are the 25 results: - PG-FOCUS-WKH-3565 / Nongprat Lynti / EASTERN WEST KHASI HILLS - payments: 2, memberships: 201, amount disbursed: 1,005,000, groups qualifying: 541 - PG-FOCUS-SWGH-780 / Doram Pg / SOUTH WEST GARO HILLS - payments: 2, memberships: 40, amount disbursed: 200,000, groups qualifying: 541 - PG-FOCUS-NGH-3003 / Rangsang / NORTH GARO HILLS - payments: 2, memberships: 40, amount disbursed: 200,000, groups qualifying: 541 - PG-FOCUS-EKH-2613 / Umtyrkhow Pg / EAST KHASI HILLS - payments: 2, memberships: 40, amount disbursed: 200,000, groups qualifying: 541 - PG-FOCUS-NGH-2508 / Evergreen Producer Group / NORTH G | G21: SELECT pg_id, MAX(pg_name) AS pg_name, lgd_district, COUNT(*) AS payments, SUM(no_of_pg_members) AS memberships, SUM(amount_disbursed) AS amount_disbursed, COUNT(*) OVER () AS groups_qualifying FROM curated.v_focus_legacy GROUP BY pg_id, lgd_district HAVING SUM(amount_disbursed) > 100000 ORDER BY amount_disbursed DESC LIMIT 25 | H21: 541 PGs with cumulative receipts > Rs 1,00,000 (Rs 1,05,000 to Rs 10,05,000); 1 single payment > Rs 1 lakh | I21: 541 PGs (cumulative); 1 single payment (Rs 9,50,000) | J21: MATCH | K21: MATCH | L21: PASS | M21: FAIL | N21: FAIL | O21: FIXED | P21: FIXED (FAIL in rounds 1 and 2). The answer now leads with '541 producer groups match in total; the top 25 are shown below' (DB 541 = Raw 541), followed by the list (top: Nongprat Lynti Rs 10,05,000 = raw). When a Focus Legacy list stops at its LIMIT, the true total is carried into the answer and is guaranteed to lead it. Passed 3 of 3 runs. | Q21: View proof
A22: TC-20 | B22: Retrieve remittances within a specific date range | C22: Show me all remittances made between April and June 2025. | D22: 1: Focus Legacy (producer group payments) | E22: data | F22: Focus Legacy shows 5,106 remittances made between April and June 2025. The total amount disbursed for this period was 95,440,000.00. | G22: SELECT COUNT(*) AS payments, SUM(amount_disbursed) AS amount_disbursed, MIN(date_of_remittance) AS first_payment, MAX(date_of_remittance) AS last_payment FROM curated.v_focus_legacy WHERE date_of_remittance >= DATE '2025-04-01' AND date_of_remittance < DATE '2025-07-01' LIMIT 1000 | H22: 5,106 payments, Rs 9,54,40,000 (18, 20, 26 Jun 2025) | I22: 5,106 rows, Rs 9,54,40,000 | J22: MATCH | K22: MATCH | L22: PASS | M22: FAIL | N22: PASS | O22: FIXED | P22: FIXED (intermittent in round 2). 5,106 remittances, Rs 9,54,40,000 = DB = Raw. The verifier's false 'prohibited join' complaints on one-table queries are now discarded, so no attempt is lost. Passed 3 of 3 runs. | Q22: View proof
... A31: TC-28blk | B31: Count Producer Groups by constituency (supplementary: Songsak block chip) | C31: How many Producer Groups are mapped to Songsak? | D31: 2: The Songsak C&RD block > All financial years combined | E31: data | F31: Songsak block has 344 Producer Groups mapped across all financial years. | G31: SELECT COUNT(DISTINCT pg_id) AS producer_groups FROM curated.v_focus_legacy WHERE lgd_block = 'SONGSAK' LIMIT 1000 | H31: 344 PGs (lgd_block = SONGSAK) | I31: 344 PGs (mapped_block_lgd_name = Songsak) | J31: MATCH | K31: MATCH | L31: PASS | M31: PASS | N31: not run | O31: same | P31: SUPPLEMENTARY, not counted in the 28: the same TC-28 question, choosing the first chip 'The Songsak C&RD block'. FIXED by the DB change: round 1 answered 338; now 344 = DB = Raw. Passed 3 of 3 runs. | Q31: View proof

Sheet DB vs Raw Reconciliation
A1: Focus Legacy - DB (curated.v_focus_legacy) vs raw file (Focus Legacy to share to BLH.csv)
A3: Check | B3: Raw CSV | C3: DB | D3: Difference (DB - Raw) | E3: Status | F3: Note
A4: Row count | B4: 14569 | C4: 14569 | D4: =C4-B4 -> 0 | E4: =IF(C4=B4,"MATCH","MISMATCH") -> MATCH | F4: raw id = DB source_row_id, 1:1
A5: Total amount (Rs) | B5: 510105000 | C5: 510105000 | D5: =C5-B5 -> 0 | E5: =IF(C5=B5,"MATCH","MISMATCH") -> MATCH
A6: Total PG members (memberships) | B6: 102021 | C6: 102021 | D6: =C6-B6 -> 0 | E6: =IF(C6=B6,"MATCH","MISMATCH") -> MATCH
A7: Distinct pg_id | B7: 11906 | C7: 11906 | D7: =C7-B7 -> 0 | E7: =IF(C7=B7,"MATCH","MISMATCH") -> MATCH
A8: Distinct PG names | B8: 10678 | C8: 9452 | D8: =C8-B8 -> -1226 | E8: =IF(C8=B8,"MATCH","MISMATCH") -> MISMATCH | F8: DB keeps one current name per pg_id (1,634 pg_ids have >1 spelling in raw) - by design, README 4.8
A9: Rows where pg_id differs | B9: 0 | C9: 0 | D9: =C9-B9 -> 0 | E9: =IF(C9=B9,"MATCH","MISMATCH") -> MATCH | F9: row-level compare
A10: Rows where members differ | B10: 0 | C10: 0 | D10: =C10-B10 -> 0 | E10: =IF(C10=B10,"MATCH","MISMATCH") -> MATCH | F10: row-level compare
A11: Rows where amount differs | B11: 0 | C11: 0 | D11: =C11-B11 -> 0 | E11: =IF(C11=B11,"MATCH","MISMATCH") -> MATCH | F11: row-level compare
A12: Rows where district differs | B12: 0 | C12: 0 | D12: =C12-B12 -> 0 | E12: =IF(C12=B12,"MATCH","MISMATCH") -> MATCH | F12: DB upper-cases names
A13: Rows where financial year differs | B13: 0 | C13: 0 | D13: =C13-B13 -> 0 | E13: =IF(C13=B13,"MATCH","MISMATCH") -> MATCH
A14: Rows where constituency differs (DB via dim_geography.ac_name) | B14: 0 | C14: 0 | D14: =C14-B14 -> 0 | E14: =IF(C14=B14,"MATCH","MISMATCH") -> MATCH | F14: 13,468 rows with a constituency
A15: Rows with block NULL | B15: 88 | C15: 88 | D15: =C15-B15 -> 0 | E15: =IF(C15=B15,"MATCH","MISMATCH") -> MATCH | F15: Round 1: 1,101 (1,013 rows had lost their block). FIXED in round 2: the 88 remaining are blank in the raw file too
A16: Rows where block differs (raw block present) | B16: 0 | C16: 0 | D16: =C16-B16 -> 0 | E16: =IF(C16=B16,"MATCH","MISMATCH") -> MATCH | F16: Round 1: 1,013. FIXED in round 2
A17: Rows with block_name_raw populated (audit copy of source block) | B17: 14481 | C17: 0 | D17: =C17-B17 -> -14481 | E17: =IF(C17=B17,"MATCH","MISMATCH") -> MISMATCH | F17: NEW in round 2: the DB change emptied this audit column on every row (round 1: 14,481 populated). Not used by the bot; no test affected
A18: Rows with district_name_raw populated (audit copy of source district) | B18: 14569 | C18: 0 | D18: =C18-B18 -> -14569 | E18: =IF(C18=B18,"MATCH","MISMATCH") -> MISMATCH | F18: NEW in round 2: emptied on every row (round 1: 14,569 populated). Not used by the bot; no test affected
A19: Rows with no remittance date | B19: 171 | C19: 171 | D19: =C19-B19 -> 0 | E19: =IF(C19=B19,"MATCH","MISMATCH") -> MATCH
A20: Rows where PG name differs from raw | B20: 0 | C20: 1636 | D20: =C20-B20 -> 1636 | E20: =IF(C20=B20,"MATCH","MISMATCH") -> MISMATCH | F20: current-name normalisation, see Distinct PG names
A21: Amount FY 2021-22 (Rs) | B21: 68235000 | C21: 68235000 | D21: =C21-B21 -> 0 | E21: =IF(C21=B21,"MATCH","MISMATCH") -> MATCH
A22: Amount FY 2022-23 (Rs) | B22: 141790000 | C22: 141790000 | D22: =C22-B22 -> 0 | E22: =IF(C22=B22,"MATCH","MISMATCH") -> MATCH
A23: Amount FY 2024-25 (Rs) | B23: 114990000 | C23: 114990000 | D23: =C23-B23 -> 0 | E23: =IF(C23=B23,"MATCH","MISMATCH") -> MATCH
A24: Amount FY 2025-26 (Rs) | B24: 185090000 | C24: 185090000 | D24: =C24-B24 -> 0 | E24: =IF(C24=B24,"MATCH","MISMATCH") -> MATCH
A25: PGs in East Garo Hills | B25: 928 | C25: 928 | D25: =C25-B25 -> 0 | E25: =IF(C25=B25,"MATCH","MISMATCH") -> MATCH
A26: PGs in East Jaintia Hills | B26: 626 | C26: 626 | D26: =C26-B26 -> 0 | E26: =IF(C26=B26,"MATCH","MISMATCH") -> MATCH
A27: PGs in East Khasi Hills | B27: 909 | C27: 909 | D27: =C27-B27 -> 0 | E27: =IF(C27=B27,"MATCH","MISMATCH") -> MATCH
A28: PGs in Eastern West Khasi Hills | B28: 792 | C28: 792 | D28: =C28-B28 -> 0 | E28: =IF(C28=B28,"MATCH","MISMATCH") -> MATCH
A29: PGs in North Garo Hills | B29: 1173 | C29: 1173 | D29: =C29-B29 -> 0 | E29: =IF(C29=B29,"MATCH","MISMATCH") -> MATCH
A30: PGs in Ri Bhoi | B30: 955 | C30: 955 | D30: =C30-B30 -> 0 | E30: =IF(C30=B30,"MATCH","MISMATCH") -> MATCH
A31: PGs in South Garo Hills | B31: 532 | C31: 532 | D31: =C31-B31 -> 0 | E31: =IF(C31=B31,"MATCH","MISMATCH") -> MATCH
A32: PGs in South West Garo Hills | B32: 794 | C32: 794 | D32: =C32-B32 -> 0 | E32: =IF(C32=B32,"MATCH","MISMATCH") -> MATCH
... A36: PGs in West Khasi Hills | B36: 926 | C36: 926 | D36: =C36-B36 -> 0 | E36: =IF(C36=B36,"MATCH","MISMATCH") -> MATCH

Sheet Proof Screenshots
A1: TC-01 - PASS
A45: TC-02 - PASS
A83: TC-03 - PASS
A121: TC-04 - PASS
A154: TC-05 - PASS
A191: TC-06 - PASS
A222: TC-07 - PASS
A260: TC-08 - PASS
A296: TC-09 - PASS
A342: TC-10 - PASS
A388: TC-11 - PASS
A425: TC-12 - PASS
... A1202: TC-28blk - PASS
